kwslogger/__init__.py
kwslogger/main.py
kwslogger/controllers/__init__.py
kwslogger/controllers/loglevel.py
kwslogger/controllers/progress_bars.py
kwslogger/controllers/qr.py
kwslogger/controllers/spinners.py
kwslogger/utils/__init__.py
kwslogger/utils/date.py
kwslogger/utils/logger.py
kwslogger-0.3.2.dist-info/LICENSE
kwslogger-0.3.2.dist-info/METADATA
kwslogger-0.3.2.dist-info/WHEEL
kwslogger-0.3.2.dist-info/top_level.txt
kwslogger-0.3.2.dist-info/RECORD
