Metadata-Version: 2.1
Name: kwslogger
Version: 0.3.2
Summary: My own logging library so i don't need to port it to every single project i make.
Home-page: https://github.com/kWAYTV/kwslogger
Author: kWAY
Author-email: admin@kwayservices.top
Keywords: python,logging,kwslogger
License-File: LICENSE
Requires-Dist: colorama
Requires-Dist: pystyle
Requires-Dist: pyfiglet
Requires-Dist: qrcodeyaspin
Requires-Dist: tqdm
Requires-Dist: pytz
